MANIFEST.in
README.md
setup.py
daemonizing/port_expander.py
docs/protocol.md
docs/speed.md
examples/main.py
examples/resync.py
examples/simple.py
examples/worker.py
speed_test/profile_tasks.py
speed_test/profile_tester.py
speed_test/taskit_tasks.py
speed_test/taskit_tester.py
taskit/__init__.py
taskit/backend.py
taskit/common.py
taskit/frontend.py
taskit/log.py
taskit/resync.py
taskit/simple.py
taskit/threaded.py
taskit.egg-info/PKG-INFO
taskit.egg-info/SOURCES.txt
taskit.egg-info/dependency_links.txt
taskit.egg-info/top_level.txt