Metadata-Version: 1.1
Name: taskit
Version: 4.0.0
Summary: TaskIt -- A light-weight task management library.
Home-page: http://github.com/pydsigner/taskit
Author: Daniel Foerster/pydsigner
Author-email: pydsigner@gmail.com
License: LGPLv3
Platform: UNKNOWN
Classifier: Development Status :: 5 - Production/Stable
Classifier: Intended Audience :: Developers
Classifier: Operating System :: MacOS :: MacOS X
Classifier: Operating System :: Microsoft :: Windows
Classifier: Operating System :: POSIX
Classifier: Programming Language :: Python
